ase_koopmans/__init__.py
ase_koopmans/__main__.py
ase_koopmans/atom.py
ase_koopmans/atoms.py
ase_koopmans/autoneb.py
ase_koopmans/cell.py
ase_koopmans/constraints.py
ase_koopmans/dimer.py
ase_koopmans/eos.py
ase_koopmans/formula.py
ase_koopmans/neb.py
ase_koopmans/neighborlist.py
ase_koopmans/nomad.py
ase_koopmans/outputs.py
ase_koopmans/parallel.py
ase_koopmans/phasediagram.py
ase_koopmans/phonons.py
ase_koopmans/quaternions.py
ase_koopmans/structure.py
ase_koopmans/symbols.py
ase_koopmans/thermochemistry.py
ase_koopmans/units.py
ase_koopmans/build/__init__.py
ase_koopmans/build/attach.py
ase_koopmans/build/bulk.py
ase_koopmans/build/general_surface.py
ase_koopmans/build/molecule.py
ase_koopmans/build/ribbon.py
ase_koopmans/build/root.py
ase_koopmans/build/rotate.py
ase_koopmans/build/supercells.py
ase_koopmans/build/surface.py
ase_koopmans/build/surfaces_with_termination.py
ase_koopmans/build/tools.py
ase_koopmans/build/tube.py
ase_koopmans/build/voids.py
ase_koopmans/calculators/__init__.py
ase_koopmans/calculators/abinit.py
ase_koopmans/calculators/acemolecule.py
ase_koopmans/calculators/acn.py
ase_koopmans/calculators/aims.py
ase_koopmans/calculators/amber.py
ase_koopmans/calculators/ase_qmmm_manyqm.py
ase_koopmans/calculators/autodetect.py
ase_koopmans/calculators/calculator.py
ase_koopmans/calculators/castep.py
ase_koopmans/calculators/checkpoint.py
ase_koopmans/calculators/combine_mm.py
ase_koopmans/calculators/counterions.py
ase_koopmans/calculators/cp2k.py
ase_koopmans/calculators/crystal.py
ase_koopmans/calculators/demonnano.py
ase_koopmans/calculators/dftb.py
ase_koopmans/calculators/dftd3.py
ase_koopmans/calculators/dmol.py
ase_koopmans/calculators/eam.py
ase_koopmans/calculators/elk.py
ase_koopmans/calculators/emt.py
ase_koopmans/calculators/excitation_list.py
ase_koopmans/calculators/exciting.py
ase_koopmans/calculators/ff.py
ase_koopmans/calculators/fleur.py
ase_koopmans/calculators/gamess_us.py
ase_koopmans/calculators/gaussian.py
ase_koopmans-0.1.11.dist-info/licenses/COPYING
ase_koopmans-0.1.11.dist-info/licenses/COPYING.LESSER
ase_koopmans-0.1.11.dist-info/licenses/LICENSE
ase_koopmans-0.1.11.dist-info/METADATA
ase_koopmans-0.1.11.dist-info/WHEEL
ase_koopmans-0.1.11.dist-info/top_level.txt
ase_koopmans-0.1.11.dist-info/RECORD
