Metadata-Version: 2.4
Name: ase-koopmans
Version: 0.1.11
Summary: Atomic Simulation Environment for Koopmans
Home-page: https://github.com/elinscott/ase_koopmans
Maintainer: Edward Linscott
Maintainer-email: edwardlinscott@gmail.com
License: LGPLv2.1+
Platform: unix
Classifier: Development Status :: 2 - Pre-Alpha
Classifier: License :: OSI Approved :: GNU Lesser General Public License v2 or later (LGPLv2+)
Classifier: Operating System :: OS Independent
Classifier: Programming Language :: Python :: 3
Classifier: Programming Language :: Python :: 3.6
Classifier: Programming Language :: Python :: 3.7
Classifier: Topic :: Scientific/Engineering :: Physics
License-File: LICENSE
License-File: COPYING
License-File: COPYING.LESSER
Requires-Dist: numpy>=1.11.3
Requires-Dist: scipy>=0.18.1
Requires-Dist: matplotlib>=2.0.0
Provides-Extra: docs
Requires-Dist: sphinx; extra == "docs"
Requires-Dist: sphinx_rtd_theme; extra == "docs"
Requires-Dist: pillow; extra == "docs"
Provides-Extra: test
Requires-Dist: pytest>=3.6.1; extra == "test"
Requires-Dist: pytest-xdist>=1.22.1; extra == "test"
Dynamic: classifier
Dynamic: description
Dynamic: home-page
Dynamic: license
Dynamic: license-file
Dynamic: maintainer
Dynamic: maintainer-email
Dynamic: platform
Dynamic: provides-extra
Dynamic: requires-dist
Dynamic: summary
